picocosmo/CosmoGuiUi.py
picocosmo/PulseFilter.py
picocosmo/__init__.py
picocosmo/_version_info.py
picocosmo/runCosmoDAQ.py
picocosmo/runCosmoUi.py
picocosmo/doc/Hilfe.html
picocosmo/doc/help.html
picocosmo/images/CosmoKanne_icon.png
picocosmo/images/CosmoPanels_icon.png
picocosmo/images/application-exit.jpg
picocosmo/images/flagDE.png
picocosmo/images/flagUK.png
picocosmo/images/open-folder.jpg
picocosmo/images/picoCosmo_iconic.jpg
picocosmo/images/start.jpg
picocosmo-0.9.0.data/scripts/CosmoGui.py
picocosmo-0.9.0.data/scripts/runCosmo.py
picocosmo-0.9.0.dist-info/LICENSE
picocosmo-0.9.0.dist-info/METADATA
picocosmo-0.9.0.dist-info/WHEEL
picocosmo-0.9.0.dist-info/top_level.txt
picocosmo-0.9.0.dist-info/RECORD
