Metadata-Version: 2.1
Name: picocosmo
Version: 0.9.0
Summary: Analysis of waveforms from cosmic ray detectors
Home-page: https://www.etp.kit.edu/~quast/
Author: Guenter Quast
Author-email: Guenter.Quast@online.de
License: GNU Public Licence
Platform: UNKNOWN
Classifier: Development Status :: 4 - Beta
Classifier: Programming Language :: Python :: 3.6
Classifier: Programming Language :: Python :: 3.7
Classifier: Programming Language :: Python :: 3.8
Classifier: Programming Language :: Python :: 3.9
License-File: LICENSE
